Metadata-Version: 2.1
Name: fugue-warehouses
Version: 0.0.4
Summary: Fugue data warehouses integration
Home-page: http://github.com/fugue-project/fugue-warehouses
Author: The Fugue Development Team
Author-email: hello@fugue.ai
License: Apache-2.0
Keywords: fugue data warehouses bigquery trino sql
Platform: UNKNOWN
Classifier: Development Status :: 3 - Alpha
Classifier: Intended Audience :: Developers
Classifier: Topic :: Software Development :: Libraries :: Python Modules
Classifier: License :: OSI Approved :: Apache Software License
Classifier: Programming Language :: Python :: 3.8
Classifier: Programming Language :: Python :: 3.9
Classifier: Programming Language :: Python :: 3.10
Classifier: Programming Language :: Python :: 3 :: Only
Requires-Python: >=3.8
Provides-Extra: bigquery
Requires-Dist: fugue[ibis] <0.9,>=0.8.4 ; extra == 'bigquery'
Requires-Dist: fs-gcsfs ; extra == 'bigquery'
Requires-Dist: pandas-gbq ; extra == 'bigquery'
Requires-Dist: google-auth ; extra == 'bigquery'
Requires-Dist: db-dtypes ; extra == 'bigquery'
Requires-Dist: ibis-framework[bigquery] ; extra == 'bigquery'
Provides-Extra: ray
Requires-Dist: fugue[ray] <0.9,>=0.8.4 ; extra == 'ray'
Provides-Extra: snowflake
Requires-Dist: fugue[ibis] <0.9,>=0.8.4 ; extra == 'snowflake'
Requires-Dist: ibis-framework[snowflake] ; extra == 'snowflake'
Provides-Extra: trino
Requires-Dist: fugue[ibis] <0.9,>=0.8.4 ; extra == 'trino'
Requires-Dist: ibis-framework[trino] ; extra == 'trino'
